foxmock/__init__.py
foxmock-0.1.5.dist-info/LICENSE
foxmock-0.1.5.dist-info/METADATA
foxmock-0.1.5.dist-info/WHEEL
foxmock-0.1.5.dist-info/top_level.txt
foxmock-0.1.5.dist-info/RECORD
