Metadata-Version: 2.1
Name: foxmock
Version: 0.1.5
Summary: A simple and flixible mock library for python
Home-page: https://github.com/wangxiaochuang/foxmock
Author: wangxiaochuang
Author-email: jackstrawxiaoxin@gmail.com
License: MIT
Platform: UNKNOWN
Classifier: License :: OSI Approved :: MIT License
Classifier: Programming Language :: Python
Classifier: Programming Language :: Python :: 3
Classifier: Programming Language :: Python :: 3.6
Classifier: Programming Language :: Python :: Implementation :: CPython
Classifier: Programming Language :: Python :: Implementation :: PyPy
Requires-Python: >=3.6.0
License-File: LICENSE
Provides-Extra: tests
Requires-Dist: pytest ; extra == 'tests'
